print_wp_sources.py
print_wp_sources-0.5.dist-info/METADATA
print_wp_sources-0.5.dist-info/WHEEL
print_wp_sources-0.5.dist-info/entry_points.txt
print_wp_sources-0.5.dist-info/licenses/LICENSE
print_wp_sources-0.5.dist-info/RECORD
