Metadata-Version: 2.3
Name: print-wp-sources
Version: 0.5
Summary: Print sources from Wikipedia or Wikinews articles to stdout.
Project-URL: Homepage, https://codeberg.org/hyperreal/print-wp-sources
Project-URL: Issues, https://codeberg.org/hyperreal/print-wp-sources/issues
Author-email: Jeffrey Serio <hyperreal@fedoraproject.org>
Classifier: License :: OSI Approved :: GNU General Public License v3 or later (GPLv3+)
Classifier: Operating System :: OS Independent
Classifier: Programming Language :: Python :: 3
Requires-Python: >=3.10
Requires-Dist: beautifulsoup4>=4.12.3
Requires-Dist: requests>=2.32.3
